LICENSE
MANIFEST.in
README.md
requirements.txt
setup.py
chef_cli.egg-info/PKG-INFO
chef_cli.egg-info/SOURCES.txt
chef_cli.egg-info/dependency_links.txt
chef_cli.egg-info/entry_points.txt
chef_cli.egg-info/requires.txt
chef_cli.egg-info/top_level.txt
chefcli/ChefParser.py
chefcli/ChefRequest.py
chefcli/__main__.py
screenshots/CollegeRanking.png
screenshots/Compare.png
screenshots/ProblemStatement.png
screenshots/RecommendProblem.png
screenshots/SampleSubmit.png
screenshots/SubmissionGraph.png
screenshots/UserInfo.png
screenshots/logo.png