Metadata-Version: 2.1
Name: chef-cli
Version: 1.0.1
Summary: CodeChef command line interface. ChefCLI helps competitive coders to search, view,                 and submit problems in CodeChef.
Home-page: https://github.com/mkfeuhrer/chef-cli
Author: Abhey Rana
Author-email: abhey.mnnit@gmail.com
License: MIT
Keywords: chef-cli codechef cli programming
Platform: UNKNOWN
Requires: decouple
Requires: mdv
Requires: requests
Requires: termgraph
Requires: termcolor
Requires-Python: >=3.5
